defirl/__init__.py
defirl/bid50_epitrans.npy
defirl/bid50_q_table.npy
defirl/bid50_state_to_index.npy
defirl/bid74_epitrans.pkl
defirl/bid74_q_table.pkl
defirl/bid74_state_to_index.pkl
defirl/bid86_epitrans.pkl
defirl/bid86_q_table.pkl
defirl/bid86_state_to_index.pkl
defirl/bids2_epitrans.pkl
defirl/bids2_q_table.pkl
defirl/bids2_state_to_index.pkl
defirl/bids_epitrans.pkl
defirl/bids_q_table.pkl
defirl/bids_state_to_index.pkl
defirl/rl.py
defirl/rlhf_long.py
defirl/rlhf_short.py
defirl-0.10.13.dist-info/licenses/LICENSE
defirl-0.10.13.dist-info/METADATA
defirl-0.10.13.dist-info/WHEEL
defirl-0.10.13.dist-info/top_level.txt
defirl-0.10.13.dist-info/RECORD
